{
  "generatedAt": "2026-04-13T15:16:05.839Z",
  "period": {
    "current": "최근 7일",
    "previous": "7-14일 전"
  },
  "risingCategories": [
    {
      "category": "Education",
      "currentCount": 4,
      "previousCount": 1,
      "changePercent": 300,
      "changeDirection": "up",
      "apps": [
        "OpenSky Homeschool Planner",
        "EchoFlow: AI English Shadowing",
        "FROS OSCE Log",
        "Sakura Renrakumou"
      ],
      "avgScore": 7.699999999999999
    },
    {
      "category": "Lifestyle",
      "currentCount": 10,
      "previousCount": 3,
      "changePercent": 233,
      "changeDirection": "up",
      "apps": [
        "ChirpPal - Parrot Training",
        "Knitting Notebook",
        "Apartment-i",
        "AI Hair Transplant & Analysis",
        "Tidy AI: Snap & Clean",
        "Jesse — Texting Assistant",
        "Apartment-i - Apartment App",
        "AutistaAI",
        "BreakTodo - AI 拆分任务 | ADHD 필备",
        "friendkeeper"
      ],
      "avgScore": 7.95
    },
    {
      "category": "Public Safety",
      "currentCount": 3,
      "previousCount": 1,
      "changePercent": 200,
      "changeDirection": "up",
      "apps": [
        "CrimeRadar: Dispatch Alerts",
        "CrimeRadar: Dispatch Alerts",
        "CrimeRadar: Dispatch Alerts"
      ],
      "avgScore": 7.433333333333334
    },
    {
      "category": "Entertainment",
      "currentCount": 5,
      "previousCount": 2,
      "changePercent": 150,
      "changeDirection": "up",
      "apps": [
        "Dootchi: Chat with AI Chars",
        "iDrama – Short Dramas & Reels",
        "VibeShort: AI Comic Dramas",
        "VibeShort: AI Comic Dramas",
        "VibeShort: AI Comic Dramas"
      ],
      "avgScore": 8.02
    },
    {
      "category": "Shopping",
      "currentCount": 4,
      "previousCount": 2,
      "changePercent": 100,
      "changeDirection": "up",
      "apps": [
        "Queenit – Lifestyle Shop for Stylish Adults",
        "Fallcent – Price Alerts, Comparisons, Hot Deals",
        "The Fair – Golfwear & Luxury Resale",
        "BuildZap: Materials in Minutes"
      ],
      "avgScore": 7.175
    },
    {
      "category": "Social",
      "currentCount": 2,
      "previousCount": 1,
      "changePercent": 100,
      "changeDirection": "up",
      "apps": [
        "PolyBuzz: Chat with AI Friends",
        "zeta - AI Character Roleplay Chat"
      ],
      "avgScore": 7.1
    },
    {
      "category": "Graphics/Design",
      "currentCount": 1,
      "previousCount": 0,
      "changePercent": 100,
      "changeDirection": "up",
      "apps": [
        "Re:Home - AI Design Visualiser"
      ],
      "avgScore": 8.7
    },
    {
      "category": "Advertising & Design",
      "currentCount": 1,
      "previousCount": 0,
      "changePercent": 100,
      "changeDirection": "up",
      "apps": [
        "Loopit - Make Playables"
      ],
      "avgScore": 8.9
    },
    {
      "category": "News & Safety",
      "currentCount": 1,
      "previousCount": 0,
      "changePercent": 100,
      "changeDirection": "up",
      "apps": [
        "CrimeRadar: Dispatch Alerts"
      ],
      "avgScore": 7.9
    },
    {
      "category": "Social • AI Chat",
      "currentCount": 1,
      "previousCount": 0,
      "changePercent": 100,
      "changeDirection": "up",
      "apps": [
        "zeta - AI Characters Roleplay Chat"
      ],
      "avgScore": 7.7
    },
    {
      "category": "News",
      "currentCount": 1,
      "previousCount": 0,
      "changePercent": 100,
      "changeDirection": "up",
      "apps": [
        "Wisp — News Without Drama"
      ],
      "avgScore": 7.4
    },
    {
      "category": "Design & Creativity",
      "currentCount": 1,
      "previousCount": 0,
      "changePercent": 100,
      "changeDirection": "up",
      "apps": [
        "Loopit - Make Playables"
      ],
      "avgScore": 8.2
    },
    {
      "category": "Reference",
      "currentCount": 1,
      "previousCount": 0,
      "changePercent": 100,
      "changeDirection": "up",
      "apps": [
        "Minti — Collection Tracker"
      ],
      "avgScore": 6.8
    },
    {
      "category": "Video & Creator Tools",
      "currentCount": 1,
      "previousCount": 0,
      "changePercent": 100,
      "changeDirection": "up",
      "apps": [
        "Loopit - Make Playables"
      ],
      "avgScore": 8
    },
    {
      "category": "Marketing & Design",
      "currentCount": 1,
      "previousCount": 0,
      "changePercent": 100,
      "changeDirection": "up",
      "apps": [
        "Loopit - Make Playables"
      ],
      "avgScore": 8.8
    },
    {
      "category": "Security & Fraud Prevention",
      "currentCount": 1,
      "previousCount": 0,
      "changePercent": 100,
      "changeDirection": "up",
      "apps": [
        "시티즌코난 - 보이스피싱,스미싱,피싱아이즈,사기예방"
      ],
      "avgScore": 8.2
    },
    {
      "category": "Entertainment & Social",
      "currentCount": 1,
      "previousCount": 0,
      "changePercent": 100,
      "changeDirection": "up",
      "apps": [
        "크랙 - 즉흥 서사 플레이, AI 채팅"
      ],
      "avgScore": 7.6
    },
    {
      "category": "Personalization & Launcher",
      "currentCount": 1,
      "previousCount": 0,
      "changePercent": 100,
      "changeDirection": "up",
      "apps": [
        "Easy Homescreen"
      ],
      "avgScore": 7.8
    },
    {
      "category": "Personalization",
      "currentCount": 3,
      "previousCount": 2,
      "changePercent": 50,
      "changeDirection": "up",
      "apps": [
        "Free Talk Stickers - Personal Stickers",
        "Easy Homescreen",
        "Easy Homescreen"
      ],
      "avgScore": 7.366666666666667
    },
    {
      "category": "Utilities",
      "currentCount": 6,
      "previousCount": 5,
      "changePercent": 20,
      "changeDirection": "up",
      "apps": [
        "ZKP Storage",
        "record STT onDevice",
        "Kawatta — Website Change Monitor",
        "BugLens - Insect Identifier",
        "BoilerSteamNavigator",
        "Orders: Manage DMs & Sales"
      ],
      "avgScore": 7.816666666666666
    }
  ],
  "decliningCategories": [
    {
      "category": "Productivity",
      "currentCount": 6,
      "previousCount": 8,
      "changePercent": -25,
      "changeDirection": "down",
      "apps": [
        "hrsly: Shift & Pay Tracker",
        "Aura: ADHD Focus Timer & Flow",
        "Easy Mail - Email Launcher",
        "PDF Converter: HWP Viewer & Hangul Viewer",
        "LensLedger",
        "AquaKettle Thickness Ledger"
      ],
      "avgScore": 7.416666666666667
    },
    {
      "category": "Health & Fitness",
      "currentCount": 5,
      "previousCount": 7,
      "changePercent": -29,
      "changeDirection": "down",
      "apps": [
        "Tina - For Life With Scoliosis",
        "Glucose Tracker - GDM Diary",
        "RePattern",
        "머니워크 -돈버는 건강관리, 걷기로 용돈벌기, 현금인출",
        "GLP Buddy: GLP-1 Companion"
      ],
      "avgScore": 7.859999999999999
    },
    {
      "category": "Security",
      "currentCount": 2,
      "previousCount": 3,
      "changePercent": -33,
      "changeDirection": "down",
      "apps": [
        "Citizen Conan",
        "Citizen Conan - Anti-Phishing & Fraud Prevention"
      ],
      "avgScore": 8.35
    },
    {
      "category": "Developer Tools",
      "currentCount": 1,
      "previousCount": 2,
      "changePercent": -50,
      "changeDirection": "down",
      "apps": [
        "DockForge - Docker Client"
      ],
      "avgScore": 6.8
    },
    {
      "category": "Food & Drink",
      "currentCount": 1,
      "previousCount": 2,
      "changePercent": -50,
      "changeDirection": "down",
      "apps": [
        "Too Good To Go"
      ],
      "avgScore": 7.8
    },
    {
      "category": "Music",
      "currentCount": 1,
      "previousCount": 4,
      "changePercent": -75,
      "changeDirection": "down",
      "apps": [
        "Ensemble Jammer"
      ],
      "avgScore": 7.8
    }
  ],
  "stableCategories": [
    {
      "category": "Medical",
      "currentCount": 1,
      "previousCount": 1,
      "changePercent": 0,
      "changeDirection": "stable",
      "apps": [
        "Kinnecta: Elderly Care & Meds"
      ],
      "avgScore": 8.2
    },
    {
      "category": "Business",
      "currentCount": 1,
      "previousCount": 1,
      "changePercent": 0,
      "changeDirection": "stable",
      "apps": [
        "SnapQuote: Fast Estimates"
      ],
      "avgScore": 6.8
    },
    {
      "category": "Graphics & Design",
      "currentCount": 1,
      "previousCount": 1,
      "changePercent": 0,
      "changeDirection": "stable",
      "apps": [
        "Douge - All-in-One Perler Bead Assistant"
      ],
      "avgScore": 7.1
    },
    {
      "category": "Safety & Alerts",
      "currentCount": 1,
      "previousCount": 1,
      "changePercent": 0,
      "changeDirection": "stable",
      "apps": [
        "CrimeRadar: Dispatch Alerts"
      ],
      "avgScore": 8.4
    },
    {
      "category": "Travel",
      "currentCount": 1,
      "previousCount": 1,
      "changePercent": 0,
      "changeDirection": "stable",
      "apps": [
        "AtlasDays: Track Country Days"
      ],
      "avgScore": 8
    }
  ],
  "hotKeywords": [
    {
      "keyword": "B2C",
      "category": "tag",
      "count": 33,
      "apps": [
        "ChirpPal - Parrot Training",
        "Kinnecta: Elderly Care & Meds",
        "OpenSky Homeschool Planner",
        "ZKP Storage",
        "Queenit – Lifestyle Shop for Stylish Adults",
        "Fallcent – Price Alerts, Comparisons, Hot Deals",
        "Dootchi: Chat with AI Chars",
        "Tina - For Life With Scoliosis",
        "Ensemble Jammer",
        "Re:Home - AI Design Visualiser",
        "Glucose Tracker - GDM Diary",
        "CrimeRadar: Dispatch Alerts",
        "iDrama – Short Dramas & Reels",
        "zeta - AI Characters Roleplay Chat",
        "Free Talk Stickers - Personal Stickers",
        "hrsly: Shift & Pay Tracker",
        "Douge - All-in-One Perler Bead Assistant",
        "RePattern",
        "Aura: ADHD Focus Timer & Flow",
        "AI Hair Transplant & Analysis",
        "Wisp — News Without Drama",
        "Easy Mail - Email Launcher",
        "머니워크 -돈버는 건강관리, 걷기로 용돈벌기, 현금인출",
        "BreakTodo - AI 拆分任务 | ADHD 필备",
        "AtlasDays: Track Country Days",
        "GLP Buddy: GLP-1 Companion",
        "friendkeeper",
        "Easy Homescreen",
        "Citizen Conan - Anti-Phishing & Fraud Prevention",
        "zeta - AI Character Roleplay Chat",
        "Too Good To Go"
      ]
    },
    {
      "keyword": "AI",
      "category": "ai",
      "count": 31,
      "apps": [
        "ChirpPal - Parrot Training",
        "EchoFlow: AI English Shadowing",
        "Dootchi: Chat with AI Chars",
        "PolyBuzz: Chat with AI Friends",
        "The Fair – Golfwear & Luxury Resale",
        "Re:Home - AI Design Visualiser",
        "zeta - AI Characters Roleplay Chat",
        "Citizen Conan",
        "VibeShort: AI Comic Dramas",
        "Douge - All-in-One Perler Bead Assistant",
        "AI Hair Transplant & Analysis",
        "Wisp — News Without Drama",
        "Easy Mail - Email Launcher",
        "Tidy AI: Snap & Clean",
        "Jesse — Texting Assistant",
        "AutistaAI",
        "BugLens - Insect Identifier",
        "시티즌코난 - 보이스피싱,스미싱,피싱아이즈,사기예방",
        "크랙 - 즉흥 서사 플레이, AI 채팅",
        "BreakTodo - AI 拆分任务 | ADHD 필备",
        "zeta - AI Character Roleplay Chat"
      ]
    },
    {
      "keyword": "1인개발가능",
      "category": "tag",
      "count": 31,
      "apps": [
        "ChirpPal - Parrot Training",
        "Tina - For Life With Scoliosis",
        "record STT onDevice",
        "Re:Home - AI Design Visualiser",
        "Glucose Tracker - GDM Diary",
        "CrimeRadar: Dispatch Alerts",
        "zeta - AI Characters Roleplay Chat",
        "Free Talk Stickers - Personal Stickers",
        "hrsly: Shift & Pay Tracker",
        "Knitting Notebook",
        "SnapQuote: Fast Estimates",
        "Easy Homescreen",
        "Douge - All-in-One Perler Bead Assistant",
        "RePattern",
        "Aura: ADHD Focus Timer & Flow",
        "Easy Mail - Email Launcher",
        "머니워크 -돈버는 건강관리, 걷기로 용돈벌기, 현금인출",
        "Kawatta — Website Change Monitor",
        "Tidy AI: Snap & Clean",
        "Jesse — Texting Assistant",
        "LensLedger",
        "BreakTodo - AI 拆分任务 | ADHD 필备",
        "AtlasDays: Track Country Days",
        "GLP Buddy: GLP-1 Companion",
        "Orders: Manage DMs & Sales",
        "friendkeeper",
        "Citizen Conan - Anti-Phishing & Fraud Prevention",
        "zeta - AI Character Roleplay Chat",
        "Too Good To Go"
      ]
    },
    {
      "keyword": "B2B",
      "category": "tag",
      "count": 16,
      "apps": [
        "record STT onDevice",
        "Loopit - Make Playables",
        "BuildZap: Materials in Minutes",
        "DockForge - Docker Client",
        "SnapQuote: Fast Estimates",
        "Kawatta — Website Change Monitor",
        "FROS OSCE Log",
        "PDF Converter: HWP Viewer & Hangul Viewer",
        "Apartment-i - Apartment App",
        "Sakura Renrakumou",
        "LensLedger",
        "BoilerSteamNavigator",
        "AquaKettle Thickness Ledger",
        "Orders: Manage DMs & Sales"
      ]
    },
    {
      "keyword": "AR",
      "category": "ar_vr",
      "count": 15,
      "apps": [
        "ChirpPal - Parrot Training",
        "Kinnecta: Elderly Care & Meds",
        "Fallcent – Price Alerts, Comparisons, Hot Deals",
        "Dootchi: Chat with AI Chars",
        "The Fair – Golfwear & Luxury Resale",
        "Glucose Tracker - GDM Diary",
        "CrimeRadar: Dispatch Alerts",
        "zeta - AI Characters Roleplay Chat",
        "Apartment-i",
        "Apartment-i - Apartment App",
        "zeta - AI Character Roleplay Chat"
      ]
    },
    {
      "keyword": "AI활용",
      "category": "tag",
      "count": 7,
      "apps": [
        "Re:Home - AI Design Visualiser",
        "zeta - AI Characters Roleplay Chat",
        "Tidy AI: Snap & Clean",
        "Jesse — Texting Assistant",
        "AutistaAI",
        "BugLens - Insect Identifier",
        "크랙 - 즉흥 서사 플레이, AI 채팅"
      ]
    },
    {
      "keyword": "콘텐츠",
      "category": "creator",
      "count": 6,
      "apps": [
        "iDrama – Short Dramas & Reels",
        "VibeShort: AI Comic Dramas",
        "Loopit - Make Playables"
      ]
    },
    {
      "keyword": "프로",
      "category": "subscription",
      "count": 4,
      "apps": [
        "ChirpPal - Parrot Training",
        "Knitting Notebook",
        "Douge - All-in-One Perler Bead Assistant",
        "Loopit - Make Playables"
      ]
    },
    {
      "keyword": "엔터테인먼트",
      "category": "tag",
      "count": 4,
      "apps": [
        "Dootchi: Chat with AI Chars",
        "VibeShort: AI Comic Dramas",
        "크랙 - 즉흥 서사 플레이, AI 채팅"
      ]
    },
    {
      "keyword": "소셜",
      "category": "social",
      "count": 4,
      "apps": [
        "PolyBuzz: Chat with AI Friends",
        "Loopit - Make Playables",
        "Orders: Manage DMs & Sales"
      ]
    },
    {
      "keyword": "헬스케어",
      "category": "tag",
      "count": 4,
      "apps": [
        "Tina - For Life With Scoliosis",
        "Glucose Tracker - GDM Diary",
        "Aura: ADHD Focus Timer & Flow",
        "GLP Buddy: GLP-1 Companion"
      ]
    },
    {
      "keyword": "커뮤니티",
      "category": "social",
      "count": 4,
      "apps": [
        "CrimeRadar: Dispatch Alerts",
        "Apartment-i",
        "Apartment-i - Apartment App"
      ]
    },
    {
      "keyword": "생산성",
      "category": "tag",
      "count": 4,
      "apps": [
        "hrsly: Shift & Pay Tracker",
        "Easy Mail - Email Launcher",
        "Kawatta — Website Change Monitor",
        "BreakTodo - AI 拆分任务 | ADHD 필备"
      ]
    },
    {
      "keyword": "접근성",
      "category": "tag",
      "count": 4,
      "apps": [
        "Easy Homescreen",
        "AutistaAI"
      ]
    },
    {
      "keyword": "자동화",
      "category": "productivity",
      "count": 4,
      "apps": [
        "Jesse — Texting Assistant",
        "BoilerSteamNavigator",
        "AquaKettle Thickness Ledger",
        "friendkeeper"
      ]
    },
    {
      "keyword": "틈새시장",
      "category": "tag",
      "count": 3,
      "apps": [
        "ChirpPal - Parrot Training",
        "Douge - All-in-One Perler Bead Assistant",
        "FROS OSCE Log"
      ]
    },
    {
      "keyword": "일정",
      "category": "productivity",
      "count": 3,
      "apps": [
        "Kinnecta: Elderly Care & Meds",
        "LensLedger",
        "GLP Buddy: GLP-1 Companion"
      ]
    },
    {
      "keyword": "사회적가치",
      "category": "tag",
      "count": 3,
      "apps": [
        "Kinnecta: Elderly Care & Meds",
        "Citizen Conan",
        "Easy Homescreen"
      ]
    },
    {
      "keyword": "시니어",
      "category": "tag",
      "count": 3,
      "apps": [
        "Queenit – Lifestyle Shop for Stylish Adults",
        "Easy Homescreen"
      ]
    },
    {
      "keyword": "1인개발어려움",
      "category": "tag",
      "count": 3,
      "apps": [
        "Ensemble Jammer",
        "Loopit - Make Playables",
        "iDrama – Short Dramas & Reels"
      ]
    }
  ],
  "pricingTrends": {
    "distribution": {
      "free": {
        "count": 21,
        "percent": 30,
        "examples": [
          "Ensemble Jammer",
          "Re:Home - AI Design Visualiser",
          "Glucose Tracker - GDM Diary"
        ]
      },
      "freemium": {
        "count": 49,
        "percent": 70,
        "examples": [
          "ChirpPal - Parrot Training",
          "Kinnecta: Elderly Care & Meds",
          "EchoFlow: AI English Shadowing"
        ]
      },
      "subscription": {
        "count": 53,
        "percent": 76,
        "examples": [
          "ChirpPal - Parrot Training",
          "Kinnecta: Elderly Care & Meds",
          "OpenSky Homeschool Planner"
        ]
      },
      "onetime": {
        "count": 9,
        "percent": 13,
        "examples": [
          "ChirpPal - Parrot Training",
          "Tina - For Life With Scoliosis",
          "record STT onDevice"
        ]
      },
      "unknown": {
        "count": 4,
        "percent": 6,
        "examples": []
      }
    },
    "dominant": {
      "model": "subscription",
      "count": 53,
      "percent": 76,
      "examples": [
        "ChirpPal - Parrot Training",
        "Kinnecta: Elderly Care & Meds",
        "OpenSky Homeschool Planner"
      ]
    },
    "insight": "구독 모델이 주류. 안정적 수익을 위한 구독 전환 전략이 중요."
  },
  "techTrends": {
    "trends": [
      {
        "tech": "ai",
        "count": 27,
        "percent": 39,
        "apps": [
          "ChirpPal - Parrot Training",
          "EchoFlow: AI English Shadowing",
          "Dootchi: Chat with AI Chars",
          "PolyBuzz: Chat with AI Friends",
          "The Fair – Golfwear & Luxury Resale"
        ]
      },
      {
        "tech": "ar_vr",
        "count": 20,
        "percent": 29,
        "apps": [
          "ChirpPal - Parrot Training",
          "Kinnecta: Elderly Care & Meds",
          "Fallcent – Price Alerts, Comparisons, Hot Deals",
          "Dootchi: Chat with AI Chars",
          "The Fair – Golfwear & Luxury Resale"
        ]
      },
      {
        "tech": "productivity",
        "count": 9,
        "percent": 13,
        "apps": [
          "Kinnecta: Elderly Care & Meds",
          "Ensemble Jammer",
          "Jesse — Texting Assistant",
          "LensLedger",
          "BoilerSteamNavigator"
        ]
      },
      {
        "tech": "creator",
        "count": 6,
        "percent": 9,
        "apps": [
          "iDrama – Short Dramas & Reels",
          "VibeShort: AI Comic Dramas",
          "Loopit - Make Playables",
          "VibeShort: AI Comic Dramas",
          "Loopit - Make Playables"
        ]
      },
      {
        "tech": "social",
        "count": 5,
        "percent": 7,
        "apps": [
          "PolyBuzz: Chat with AI Friends",
          "CrimeRadar: Dispatch Alerts",
          "Apartment-i",
          "Apartment-i - Apartment App",
          "Orders: Manage DMs & Sales"
        ]
      },
      {
        "tech": "subscription",
        "count": 3,
        "percent": 4,
        "apps": [
          "Knitting Notebook",
          "Douge - All-in-One Perler Bead Assistant",
          "Loopit - Make Playables"
        ]
      }
    ],
    "dominant": {
      "tech": "ai",
      "count": 27,
      "percent": 39,
      "apps": [
        "ChirpPal - Parrot Training",
        "EchoFlow: AI English Shadowing",
        "Dootchi: Chat with AI Chars",
        "PolyBuzz: Chat with AI Friends",
        "The Fair – Golfwear & Luxury Resale"
      ]
    },
    "emerging": [
      {
        "tech": "ar_vr",
        "count": 20,
        "percent": 29,
        "apps": [
          "ChirpPal - Parrot Training",
          "Kinnecta: Elderly Care & Meds",
          "Fallcent – Price Alerts, Comparisons, Hot Deals",
          "Dootchi: Chat with AI Chars",
          "The Fair – Golfwear & Luxury Resale"
        ]
      },
      {
        "tech": "productivity",
        "count": 9,
        "percent": 13,
        "apps": [
          "Kinnecta: Elderly Care & Meds",
          "Ensemble Jammer",
          "Jesse — Texting Assistant",
          "LensLedger",
          "BoilerSteamNavigator"
        ]
      }
    ]
  },
  "opportunities": [
    {
      "type": "rising_category",
      "title": "Education 카테고리 급부상",
      "description": "300% 증가했지만 앱 수가 적어 진입 기회",
      "confidence": "high",
      "category": "Education"
    },
    {
      "type": "rising_category",
      "title": "Public Safety 카테고리 급부상",
      "description": "200% 증가했지만 앱 수가 적어 진입 기회",
      "confidence": "high",
      "category": "Public Safety"
    },
    {
      "type": "rising_category",
      "title": "Shopping 카테고리 급부상",
      "description": "100% 증가했지만 앱 수가 적어 진입 기회",
      "confidence": "high",
      "category": "Shopping"
    },
    {
      "type": "rising_category",
      "title": "Social 카테고리 급부상",
      "description": "100% 증가했지만 앱 수가 적어 진입 기회",
      "confidence": "high",
      "category": "Social"
    },
    {
      "type": "rising_category",
      "title": "Graphics/Design 카테고리 급부상",
      "description": "100% 증가했지만 앱 수가 적어 진입 기회",
      "confidence": "high",
      "category": "Graphics/Design"
    },
    {
      "type": "rising_category",
      "title": "Advertising & Design 카테고리 급부상",
      "description": "100% 증가했지만 앱 수가 적어 진입 기회",
      "confidence": "high",
      "category": "Advertising & Design"
    },
    {
      "type": "rising_category",
      "title": "News & Safety 카테고리 급부상",
      "description": "100% 증가했지만 앱 수가 적어 진입 기회",
      "confidence": "high",
      "category": "News & Safety"
    },
    {
      "type": "rising_category",
      "title": "Social • AI Chat 카테고리 급부상",
      "description": "100% 증가했지만 앱 수가 적어 진입 기회",
      "confidence": "high",
      "category": "Social • AI Chat"
    },
    {
      "type": "rising_category",
      "title": "News 카테고리 급부상",
      "description": "100% 증가했지만 앱 수가 적어 진입 기회",
      "confidence": "high",
      "category": "News"
    },
    {
      "type": "rising_category",
      "title": "Design & Creativity 카테고리 급부상",
      "description": "100% 증가했지만 앱 수가 적어 진입 기회",
      "confidence": "high",
      "category": "Design & Creativity"
    },
    {
      "type": "rising_category",
      "title": "Reference 카테고리 급부상",
      "description": "100% 증가했지만 앱 수가 적어 진입 기회",
      "confidence": "high",
      "category": "Reference"
    },
    {
      "type": "rising_category",
      "title": "Video & Creator Tools 카테고리 급부상",
      "description": "100% 증가했지만 앱 수가 적어 진입 기회",
      "confidence": "high",
      "category": "Video & Creator Tools"
    },
    {
      "type": "rising_category",
      "title": "Marketing & Design 카테고리 급부상",
      "description": "100% 증가했지만 앱 수가 적어 진입 기회",
      "confidence": "high",
      "category": "Marketing & Design"
    },
    {
      "type": "rising_category",
      "title": "Security & Fraud Prevention 카테고리 급부상",
      "description": "100% 증가했지만 앱 수가 적어 진입 기회",
      "confidence": "high",
      "category": "Security & Fraud Prevention"
    },
    {
      "type": "rising_category",
      "title": "Entertainment & Social 카테고리 급부상",
      "description": "100% 증가했지만 앱 수가 적어 진입 기회",
      "confidence": "high",
      "category": "Entertainment & Social"
    },
    {
      "type": "rising_category",
      "title": "Personalization & Launcher 카테고리 급부상",
      "description": "100% 증가했지만 앱 수가 적어 진입 기회",
      "confidence": "high",
      "category": "Personalization & Launcher"
    },
    {
      "type": "rising_category",
      "title": "Personalization 카테고리 급부상",
      "description": "50% 증가했지만 앱 수가 적어 진입 기회",
      "confidence": "high",
      "category": "Personalization"
    },
    {
      "type": "tech_trend",
      "title": "AI 기능 통합 트렌드",
      "description": "39%의 앱이 AI 기능 포함. AI 미적용 카테고리에서 차별화 기회",
      "confidence": "high",
      "tech": "ai"
    }
  ],
  "insight": {
    "trend_summary": "Education(+300%), Public Safety(+200%), Lifestyle(+233%) 카테고리가 급성장하며 새로운 기회를 제공하고 있습니다. AI 기능 통합(39%)과 구독 모델(76%)이 주요 트렌드로 자리잡았습니다.",
    "trend_details": [
      "AI 기능 통합이 39%의 앱에서 활용되며 필수 요소로 부상",
      "구독 모델이 76%로 주요 수익화 방식으로 정착",
      "1인 개발 가능한 B2C 앱에 대한 수요 증가(33회 언급)"
    ],
    "hot_categories": [
      "Education",
      "Public Safety"
    ],
    "opportunity": "Education 카테고리는 300% 급성장했지만 앱 수가 적어(4개) 경쟁이 낮은 블루오션 시장입니다.",
    "action_item": "AI 기능을 활용한 교육용 앱을 구독 모델로 개발하여 급성장하는 Education 시장에 진입하세요.",
    "weekly_theme": "AI 교육 혁신"
  }
}