{
  "generatedAt": "2026-01-10T10:23:32.557Z",
  "period": {
    "current": "최근 7일",
    "previous": "7-14일 전"
  },
  "risingCategories": [
    {
      "category": "도구",
      "currentCount": 3,
      "previousCount": 1,
      "changePercent": 200,
      "changeDirection": "up",
      "apps": [
        "Bluetooth NumPad",
        "Image Converter - PNG JPG JPEG",
        "B Stream"
      ],
      "avgScore": 6.866666666666667
    },
    {
      "category": "도서",
      "currentCount": 1,
      "previousCount": 0,
      "changePercent": 100,
      "changeDirection": "up",
      "apps": [
        "True Epub"
      ],
      "avgScore": 6.5
    },
    {
      "category": "금융/유틸리티",
      "currentCount": 1,
      "previousCount": 0,
      "changePercent": 100,
      "changeDirection": "up",
      "apps": [
        "Unsub - Subscription Farewell"
      ],
      "avgScore": 8.2
    },
    {
      "category": "커뮤니케이션",
      "currentCount": 1,
      "previousCount": 0,
      "changePercent": 100,
      "changeDirection": "up",
      "apps": [
        "Noghteha - Mesh Messenger"
      ],
      "avgScore": 6.4
    },
    {
      "category": "쇼핑",
      "currentCount": 1,
      "previousCount": 0,
      "changePercent": 100,
      "changeDirection": "up",
      "apps": [
        "Mom Bloom"
      ],
      "avgScore": 7.6
    },
    {
      "category": "캐주얼",
      "currentCount": 4,
      "previousCount": 2,
      "changePercent": 100,
      "changeDirection": "up",
      "apps": [
        "Idle Miner: Ore Empire",
        "Star Pop Mania",
        "Run Giant Run!",
        "Runaway Jester 2"
      ],
      "avgScore": 6.75
    },
    {
      "category": "출산/육아",
      "currentCount": 1,
      "previousCount": 0,
      "changePercent": 100,
      "changeDirection": "up",
      "apps": [
        "전화번호 위치 추적기"
      ],
      "avgScore": 7.2
    },
    {
      "category": "음악/오디오",
      "currentCount": 2,
      "previousCount": 0,
      "changePercent": 100,
      "changeDirection": "up",
      "apps": [
        "Radio Me - Internet FM Player",
        "Avee Music Player (Pro)"
      ],
      "avgScore": 6.75
    },
    {
      "category": "그래픽 및 디자인",
      "currentCount": 2,
      "previousCount": 0,
      "changePercent": 100,
      "changeDirection": "up",
      "apps": [
        "Ornamenter",
        "拼豆图纸-拼豆助手 (비즈공예 도안)"
      ],
      "avgScore": 7.25
    },
    {
      "category": "퍼즐",
      "currentCount": 5,
      "previousCount": 0,
      "changePercent": 100,
      "changeDirection": "up",
      "apps": [
        "DownRight: Block Puzzle Game",
        "ねこっぽ - にほんごを学べるパズル",
        "Tap Shift: Arrow Escape Puzzle",
        "brain games 2021",
        "Drop Jewel・Block Master Blast"
      ],
      "avgScore": 6.9
    },
    {
      "category": "개인화",
      "currentCount": 1,
      "previousCount": 0,
      "changePercent": 100,
      "changeDirection": "up",
      "apps": [
        "EdgeAura"
      ],
      "avgScore": 6.8
    },
    {
      "category": "교육/AR",
      "currentCount": 1,
      "previousCount": 0,
      "changePercent": 100,
      "changeDirection": "up",
      "apps": [
        "Wear 4D+ for Android"
      ],
      "avgScore": 6.8
    },
    {
      "category": "내비게이션",
      "currentCount": 1,
      "previousCount": 0,
      "changePercent": 100,
      "changeDirection": "up",
      "apps": [
        "Taipei Meter (北錶)"
      ],
      "avgScore": 7.2
    },
    {
      "category": "지도/내비게이션",
      "currentCount": 1,
      "previousCount": 0,
      "changePercent": 100,
      "changeDirection": "up",
      "apps": [
        "Metro Palermo"
      ],
      "avgScore": 6.5
    },
    {
      "category": "스포츠",
      "currentCount": 2,
      "previousCount": 0,
      "changePercent": 100,
      "changeDirection": "up",
      "apps": [
        "Yamaha Factory Racing",
        "Yoyar - Sport News"
      ],
      "avgScore": 7.2
    },
    {
      "category": "교육/취업",
      "currentCount": 1,
      "previousCount": 0,
      "changePercent": 100,
      "changeDirection": "up",
      "apps": [
        "Crack IT Jobs"
      ],
      "avgScore": 7.6
    },
    {
      "category": "생산성",
      "currentCount": 9,
      "previousCount": 6,
      "changePercent": 50,
      "changeDirection": "up",
      "apps": [
        "BottleneckMultiMax",
        "Scan to Text OCR - Ocrly",
        "UnityPlanAI",
        "プレゼン時計 (프레젠테이션 시계)",
        "Simple Calendar - Task Tracker",
        "PixSwipe: Photo Delete Swipe",
        "잠잘시각(Time2sleep): 앱 잠금, 차단, 수면",
        "이미지를 엑셀 파일로 변환",
        "MindSet (습관 트래커)"
      ],
      "avgScore": 7.644444444444446
    },
    {
      "category": "게임",
      "currentCount": 5,
      "previousCount": 4,
      "changePercent": 25,
      "changeDirection": "up",
      "apps": [
        "LineWords: Picture Word Puzzle",
        "重构心情 (감정 재구성)",
        "WithFriendsGames",
        "Tiles In Hole: Black Hole",
        "Nightmares Labyrinth Escape"
      ],
      "avgScore": 7.359999999999999
    }
  ],
  "decliningCategories": [
    {
      "category": "금융",
      "currentCount": 2,
      "previousCount": 3,
      "changePercent": -33,
      "changeDirection": "down",
      "apps": [
        "Tawi Loans Finder",
        "DailyBudget - 하루 예산 플래너"
      ],
      "avgScore": 7.699999999999999
    },
    {
      "category": "교육",
      "currentCount": 3,
      "previousCount": 5,
      "changePercent": -40,
      "changeDirection": "down",
      "apps": [
        "Natlh-sri (Tolowa Our Stories)",
        "지구 지킴이: 일상 챌린지",
        "クレーン・デリック運転士-試験対策"
      ],
      "avgScore": 7.2
    },
    {
      "category": "라이프스타일",
      "currentCount": 5,
      "previousCount": 9,
      "changePercent": -44,
      "changeDirection": "down",
      "apps": [
        "TodoLog",
        "Aquarium Tank Tracker: AquaLog",
        "JokesChief",
        "Marketecture Live",
        "Leave+ (휴가 관리)"
      ],
      "avgScore": 7.44
    },
    {
      "category": "엔터테인먼트",
      "currentCount": 2,
      "previousCount": 5,
      "changePercent": -60,
      "changeDirection": "down",
      "apps": [
        "Manga AI - AI Comic Generator",
        "Falling Filter Challenge"
      ],
      "avgScore": 7.699999999999999
    },
    {
      "category": "소셜 네트워킹",
      "currentCount": 1,
      "previousCount": 3,
      "changePercent": -67,
      "changeDirection": "down",
      "apps": [
        "WhatsToolbox"
      ],
      "avgScore": 7.5
    },
    {
      "category": "건강 및 피트니스",
      "currentCount": 1,
      "previousCount": 4,
      "changePercent": -75,
      "changeDirection": "down",
      "apps": [
        "Daily I Am Affirmations – Lima"
      ],
      "avgScore": 7.4
    }
  ],
  "stableCategories": [
    {
      "category": "건강",
      "currentCount": 1,
      "previousCount": 1,
      "changePercent": 0,
      "changeDirection": "stable",
      "apps": [
        "Pill Time"
      ],
      "avgScore": 7.4
    },
    {
      "category": "음식 및 음료",
      "currentCount": 1,
      "previousCount": 1,
      "changePercent": 0,
      "changeDirection": "stable",
      "apps": [
        "Pink Cactus Tea"
      ],
      "avgScore": 7.6
    },
    {
      "category": "사진",
      "currentCount": 1,
      "previousCount": 1,
      "changePercent": 0,
      "changeDirection": "stable",
      "apps": [
        "iCamera : Camera for îphøne 14"
      ],
      "avgScore": 6
    },
    {
      "category": "비즈니스",
      "currentCount": 1,
      "previousCount": 1,
      "changePercent": 0,
      "changeDirection": "stable",
      "apps": [
        "Nine Work for Intune"
      ],
      "avgScore": 7.5
    },
    {
      "category": "유틸리티",
      "currentCount": 10,
      "previousCount": 11,
      "changePercent": -9,
      "changeDirection": "stable",
      "apps": [
        "KinStep",
        "Lyqd",
        "Input2Touch: Remap & Control",
        "amps kw calculator",
        "Car Tracker Premium",
        "Africa Mobile Codes",
        "Wagabond Pets",
        "TV Remote: Smart Control",
        "JBS SCANNER",
        "QuickPick – Coin Flip & Dice"
      ],
      "avgScore": 7.019999999999999
    }
  ],
  "hotKeywords": [
    {
      "keyword": "1인개발가능",
      "category": "tag",
      "count": 55,
      "apps": [
        "TodoLog",
        "True Epub",
        "LineWords: Picture Word Puzzle",
        "KinStep",
        "Lyqd",
        "Unsub - Subscription Farewell",
        "Pill Time",
        "Input2Touch: Remap & Control",
        "BottleneckMultiMax",
        "amps kw calculator",
        "重构心情 (감정 재구성)",
        "Scan to Text OCR - Ocrly",
        "Idle Miner: Ore Empire",
        "Star Pop Mania",
        "Run Giant Run!",
        "WithFriendsGames",
        "UnityPlanAI",
        "Daily I Am Affirmations – Lima",
        "Tiles In Hole: Black Hole",
        "Africa Mobile Codes",
        "Runaway Jester 2",
        "전화번호 위치 추적기",
        "Nightmares Labyrinth Escape",
        "Radio Me - Internet FM Player",
        "Aquarium Tank Tracker: AquaLog",
        "プレゼン時計 (프레젠테이션 시계)",
        "DailyBudget - 하루 예산 플래너",
        "지구 지킴이: 일상 챌린지",
        "Ornamenter",
        "Falling Filter Challenge",
        "DownRight: Block Puzzle Game",
        "Simple Calendar - Task Tracker",
        "EdgeAura",
        "Wagabond Pets",
        "WhatsToolbox",
        "Taipei Meter (北錶)",
        "JokesChief",
        "TV Remote: Smart Control",
        "ねこっぽ - にほんごを学べるパズル",
        "Bluetooth NumPad",
        "Tap Shift: Arrow Escape Puzzle",
        "Metro Palermo",
        "Image Converter - PNG JPG JPEG",
        "クレーン・デリック運転士-試験対策",
        "QuickPick – Coin Flip & Dice",
        "brain games 2021",
        "iCamera : Camera for îphøne 14",
        "PixSwipe: Photo Delete Swipe",
        "잠잘시각(Time2sleep): 앱 잠금, 차단, 수면",
        "이미지를 엑셀 파일로 변환",
        "拼豆图纸-拼豆助手 (비즈공예 도안)",
        "Leave+ (휴가 관리)",
        "MindSet (습관 트래커)",
        "Crack IT Jobs",
        "Yoyar - Sport News"
      ]
    },
    {
      "keyword": "B2C",
      "category": "tag",
      "count": 51,
      "apps": [
        "TodoLog",
        "True Epub",
        "LineWords: Picture Word Puzzle",
        "KinStep",
        "Lyqd",
        "Unsub - Subscription Farewell",
        "Pill Time",
        "Input2Touch: Remap & Control",
        "Noghteha - Mesh Messenger",
        "Manga AI - AI Comic Generator",
        "BottleneckMultiMax",
        "Mom Bloom",
        "重构心情 (감정 재구성)",
        "Car Tracker Premium",
        "Scan to Text OCR - Ocrly",
        "Idle Miner: Ore Empire",
        "WithFriendsGames",
        "UnityPlanAI",
        "Daily I Am Affirmations – Lima",
        "Tiles In Hole: Black Hole",
        "Africa Mobile Codes",
        "Runaway Jester 2",
        "Natlh-sri (Tolowa Our Stories)",
        "전화번호 위치 추적기",
        "Nightmares Labyrinth Escape",
        "Radio Me - Internet FM Player",
        "プレゼン時計 (프레젠테이션 시계)",
        "DailyBudget - 하루 예산 플래너",
        "지구 지킴이: 일상 챌린지",
        "Falling Filter Challenge",
        "Simple Calendar - Task Tracker",
        "Wagabond Pets",
        "WhatsToolbox",
        "Taipei Meter (北錶)",
        "JokesChief",
        "TV Remote: Smart Control",
        "ねこっぽ - にほんごを学べるパズル",
        "Bluetooth NumPad",
        "Tap Shift: Arrow Escape Puzzle",
        "Metro Palermo",
        "Image Converter - PNG JPG JPEG",
        "クレーン・デリック運転士-試験対策",
        "QuickPick – Coin Flip & Dice",
        "PixSwipe: Photo Delete Swipe",
        "잠잘시각(Time2sleep): 앱 잠금, 차단, 수면",
        "拼豆图纸-拼豆助手 (비즈공예 도안)",
        "Leave+ (휴가 관리)",
        "MindSet (습관 트래커)",
        "Avee Music Player (Pro)",
        "Crack IT Jobs",
        "Yoyar - Sport News"
      ]
    },
    {
      "keyword": "AR",
      "category": "ar_vr",
      "count": 12,
      "apps": [
        "Unsub - Subscription Farewell",
        "Car Tracker Premium",
        "Star Pop Mania",
        "Nightmares Labyrinth Escape",
        "Aquarium Tank Tracker: AquaLog",
        "Simple Calendar - Task Tracker",
        "Wear 4D+ for Android",
        "TV Remote: Smart Control",
        "Tap Shift: Arrow Escape Puzzle",
        "Marketecture Live",
        "Yoyar - Sport News"
      ]
    },
    {
      "keyword": "AI",
      "category": "ai",
      "count": 12,
      "apps": [
        "Manga AI - AI Comic Generator",
        "UnityPlanAI",
        "Daily I Am Affirmations – Lima",
        "DailyBudget - 하루 예산 플래너",
        "Taipei Meter (北錶)",
        "JokesChief",
        "brain games 2021",
        "이미지를 엑셀 파일로 변환"
      ]
    },
    {
      "keyword": "유틸리티",
      "category": "tag",
      "count": 10,
      "apps": [
        "Input2Touch: Remap & Control",
        "amps kw calculator",
        "プレゼン時計 (프레젠테이션 시계)",
        "EdgeAura",
        "WhatsToolbox",
        "Taipei Meter (北錶)",
        "TV Remote: Smart Control",
        "Image Converter - PNG JPG JPEG",
        "JBS SCANNER",
        "PixSwipe: Photo Delete Swipe"
      ]
    },
    {
      "keyword": "생산성",
      "category": "productivity",
      "count": 8,
      "apps": [
        "TodoLog",
        "UnityPlanAI",
        "Simple Calendar - Task Tracker",
        "Bluetooth NumPad",
        "Image Converter - PNG JPG JPEG",
        "이미지를 엑셀 파일로 변환",
        "Leave+ (휴가 관리)"
      ]
    },
    {
      "keyword": "니치마켓",
      "category": "tag",
      "count": 6,
      "apps": [
        "True Epub",
        "BottleneckMultiMax",
        "Aquarium Tank Tracker: AquaLog",
        "Ornamenter",
        "クレーン・デリック運転士-試験対策",
        "拼豆图纸-拼豆助手 (비즈공예 도안)"
      ]
    },
    {
      "keyword": "프로",
      "category": "subscription",
      "count": 4,
      "apps": [
        "Noghteha - Mesh Messenger",
        "UnityPlanAI",
        "Pink Cactus Tea",
        "PixSwipe: Photo Delete Swipe"
      ]
    },
    {
      "keyword": "하이퍼캐주얼",
      "category": "tag",
      "count": 4,
      "apps": [
        "Star Pop Mania",
        "Run Giant Run!",
        "Tiles In Hole: Black Hole",
        "Tap Shift: Arrow Escape Puzzle"
      ]
    },
    {
      "keyword": "크리에이터",
      "category": "creator",
      "count": 4,
      "apps": [
        "Ornamenter",
        "Avee Music Player (Pro)"
      ]
    },
    {
      "keyword": "콘텐츠",
      "category": "creator",
      "count": 4,
      "apps": [
        "Falling Filter Challenge",
        "Yamaha Factory Racing",
        "B Stream",
        "Avee Music Player (Pro)"
      ]
    },
    {
      "keyword": "게임",
      "category": "tag",
      "count": 4,
      "apps": [
        "DownRight: Block Puzzle Game",
        "ねこっぽ - にほんごを学べるパズル",
        "brain games 2021",
        "Drop Jewel・Block Master Blast"
      ]
    },
    {
      "keyword": "B2B",
      "category": "tag",
      "count": 4,
      "apps": [
        "Yamaha Factory Racing",
        "Marketecture Live",
        "JBS SCANNER",
        "Nine Work for Intune"
      ]
    },
    {
      "keyword": "광고수익",
      "category": "tag",
      "count": 3,
      "apps": [
        "LineWords: Picture Word Puzzle",
        "Tiles In Hole: Black Hole",
        "Drop Jewel・Block Master Blast"
      ]
    },
    {
      "keyword": "커뮤니티",
      "category": "social",
      "count": 3,
      "apps": [
        "Mom Bloom",
        "지구 지킴이: 일상 챌린지",
        "Yamaha Factory Racing"
      ]
    },
    {
      "keyword": "SaaS",
      "category": "tag",
      "count": 3,
      "apps": [
        "UnityPlanAI",
        "Pink Cactus Tea",
        "Marketecture Live"
      ]
    },
    {
      "keyword": "교육",
      "category": "tag",
      "count": 3,
      "apps": [
        "Natlh-sri (Tolowa Our Stories)",
        "クレーン・デリック運転士-試験対策",
        "brain games 2021"
      ]
    },
    {
      "keyword": "B2B가능",
      "category": "tag",
      "count": 3,
      "apps": [
        "Wear 4D+ for Android",
        "이미지를 엑셀 파일로 변환",
        "Leave+ (휴가 관리)"
      ]
    },
    {
      "keyword": "에듀테크",
      "category": "tag",
      "count": 3,
      "apps": [
        "Wear 4D+ for Android",
        "ねこっぽ - にほんごを学べるパズル",
        "Crack IT Jobs"
      ]
    },
    {
      "keyword": "캐주얼게임",
      "category": "tag",
      "count": 2,
      "apps": [
        "LineWords: Picture Word Puzzle",
        "Runaway Jester 2"
      ]
    }
  ],
  "pricingTrends": {
    "distribution": {
      "free": {
        "count": 38,
        "percent": 54,
        "examples": [
          "BottleneckMultiMax",
          "Mom Bloom",
          "amps kw calculator"
        ]
      },
      "freemium": {
        "count": 52,
        "percent": 74,
        "examples": [
          "TodoLog",
          "KinStep",
          "Lyqd"
        ]
      },
      "subscription": {
        "count": 23,
        "percent": 33,
        "examples": [
          "TodoLog",
          "KinStep",
          "Unsub - Subscription Farewell"
        ]
      },
      "onetime": {
        "count": 25,
        "percent": 36,
        "examples": [
          "True Epub",
          "LineWords: Picture Word Puzzle",
          "Lyqd"
        ]
      },
      "unknown": {
        "count": 2,
        "percent": 3,
        "examples": []
      }
    },
    "dominant": {
      "model": "freemium",
      "count": 52,
      "percent": 74,
      "examples": [
        "TodoLog",
        "KinStep",
        "Lyqd"
      ]
    },
    "insight": "프리미엄 모델 대세. 무료 사용자 → 유료 전환 퍼널 설계가 핵심."
  },
  "techTrends": {
    "trends": [
      {
        "tech": "ar_vr",
        "count": 14,
        "percent": 20,
        "apps": [
          "Lyqd",
          "Unsub - Subscription Farewell",
          "Pill Time",
          "Car Tracker Premium",
          "Star Pop Mania"
        ]
      },
      {
        "tech": "ai",
        "count": 12,
        "percent": 17,
        "apps": [
          "Manga AI - AI Comic Generator",
          "Scan to Text OCR - Ocrly",
          "Tawi Loans Finder",
          "UnityPlanAI",
          "Daily I Am Affirmations – Lima"
        ]
      },
      {
        "tech": "subscription",
        "count": 5,
        "percent": 7,
        "apps": [
          "Unsub - Subscription Farewell",
          "Noghteha - Mesh Messenger",
          "UnityPlanAI",
          "Pink Cactus Tea",
          "PixSwipe: Photo Delete Swipe"
        ]
      },
      {
        "tech": "social",
        "count": 4,
        "percent": 6,
        "apps": [
          "Yamaha Factory Racing",
          "Marketecture Live",
          "Drop Jewel・Block Master Blast",
          "拼豆图纸-拼豆助手 (비즈공예 도안)"
        ]
      },
      {
        "tech": "productivity",
        "count": 4,
        "percent": 6,
        "apps": [
          "TodoLog",
          "UnityPlanAI",
          "Aquarium Tank Tracker: AquaLog",
          "JBS SCANNER"
        ]
      },
      {
        "tech": "creator",
        "count": 3,
        "percent": 4,
        "apps": [
          "Ornamenter",
          "B Stream",
          "Avee Music Player (Pro)"
        ]
      },
      {
        "tech": "health",
        "count": 1,
        "percent": 1,
        "apps": [
          "잠잘시각(Time2sleep): 앱 잠금, 차단, 수면"
        ]
      },
      {
        "tech": "fintech",
        "count": 1,
        "percent": 1,
        "apps": [
          "Lyqd"
        ]
      }
    ],
    "dominant": {
      "tech": "ar_vr",
      "count": 14,
      "percent": 20,
      "apps": [
        "Lyqd",
        "Unsub - Subscription Farewell",
        "Pill Time",
        "Car Tracker Premium",
        "Star Pop Mania"
      ]
    },
    "emerging": [
      {
        "tech": "ar_vr",
        "count": 14,
        "percent": 20,
        "apps": [
          "Lyqd",
          "Unsub - Subscription Farewell",
          "Pill Time",
          "Car Tracker Premium",
          "Star Pop Mania"
        ]
      },
      {
        "tech": "ai",
        "count": 12,
        "percent": 17,
        "apps": [
          "Manga AI - AI Comic Generator",
          "Scan to Text OCR - Ocrly",
          "Tawi Loans Finder",
          "UnityPlanAI",
          "Daily I Am Affirmations – Lima"
        ]
      }
    ]
  },
  "opportunities": [
    {
      "type": "rising_category",
      "title": "도구 카테고리 급부상",
      "description": "200% 증가했지만 앱 수가 적어 진입 기회",
      "confidence": "high",
      "category": "도구"
    },
    {
      "type": "rising_category",
      "title": "도서 카테고리 급부상",
      "description": "100% 증가했지만 앱 수가 적어 진입 기회",
      "confidence": "high",
      "category": "도서"
    },
    {
      "type": "rising_category",
      "title": "금융/유틸리티 카테고리 급부상",
      "description": "100% 증가했지만 앱 수가 적어 진입 기회",
      "confidence": "high",
      "category": "금융/유틸리티"
    },
    {
      "type": "rising_category",
      "title": "커뮤니케이션 카테고리 급부상",
      "description": "100% 증가했지만 앱 수가 적어 진입 기회",
      "confidence": "high",
      "category": "커뮤니케이션"
    },
    {
      "type": "rising_category",
      "title": "쇼핑 카테고리 급부상",
      "description": "100% 증가했지만 앱 수가 적어 진입 기회",
      "confidence": "high",
      "category": "쇼핑"
    },
    {
      "type": "rising_category",
      "title": "캐주얼 카테고리 급부상",
      "description": "100% 증가했지만 앱 수가 적어 진입 기회",
      "confidence": "high",
      "category": "캐주얼"
    },
    {
      "type": "rising_category",
      "title": "출산/육아 카테고리 급부상",
      "description": "100% 증가했지만 앱 수가 적어 진입 기회",
      "confidence": "high",
      "category": "출산/육아"
    },
    {
      "type": "rising_category",
      "title": "음악/오디오 카테고리 급부상",
      "description": "100% 증가했지만 앱 수가 적어 진입 기회",
      "confidence": "high",
      "category": "음악/오디오"
    },
    {
      "type": "rising_category",
      "title": "그래픽 및 디자인 카테고리 급부상",
      "description": "100% 증가했지만 앱 수가 적어 진입 기회",
      "confidence": "high",
      "category": "그래픽 및 디자인"
    },
    {
      "type": "rising_category",
      "title": "개인화 카테고리 급부상",
      "description": "100% 증가했지만 앱 수가 적어 진입 기회",
      "confidence": "high",
      "category": "개인화"
    },
    {
      "type": "rising_category",
      "title": "교육/AR 카테고리 급부상",
      "description": "100% 증가했지만 앱 수가 적어 진입 기회",
      "confidence": "high",
      "category": "교육/AR"
    },
    {
      "type": "rising_category",
      "title": "내비게이션 카테고리 급부상",
      "description": "100% 증가했지만 앱 수가 적어 진입 기회",
      "confidence": "high",
      "category": "내비게이션"
    },
    {
      "type": "rising_category",
      "title": "지도/내비게이션 카테고리 급부상",
      "description": "100% 증가했지만 앱 수가 적어 진입 기회",
      "confidence": "high",
      "category": "지도/내비게이션"
    },
    {
      "type": "rising_category",
      "title": "스포츠 카테고리 급부상",
      "description": "100% 증가했지만 앱 수가 적어 진입 기회",
      "confidence": "high",
      "category": "스포츠"
    },
    {
      "type": "rising_category",
      "title": "교육/취업 카테고리 급부상",
      "description": "100% 증가했지만 앱 수가 적어 진입 기회",
      "confidence": "high",
      "category": "교육/취업"
    }
  ],
  "insight": {
    "trend_summary": "도구 카테고리가 200% 급상승. ar_vr 기술 적용 앱이 증가 중.",
    "trend_details": [
      "도구 카테고리 관심 급증",
      "'1인개발가능' 키워드 인기",
      "ar_vr 기술 트렌드 지속"
    ],
    "hot_categories": [
      "도구",
      "도서"
    ],
    "opportunity": "200% 증가했지만 앱 수가 적어 진입 기회",
    "action_item": "사용자 피드백 기반 핵심 기능 개선",
    "weekly_theme": "1인개발가능"
  }
}